contact/__init__.py
contact/contactEqualityConstraint.py
contact/qpContact.py
impactTask/__init__.py
impactTask/impactEstimator.py
impactTask/jointVelocityJumpEstimator.py
manipulatorConstraints/__init__.py
manipulatorConstraints/combinedTorqueConstraints.py
manipulatorConstraints/impactBoundConstraints.py
manipulatorConstraints/impactConstraints.py
manipulatorConstraints/impulseTorqueLimitConstraints.py
manipulatorConstraints/jointAccelerationConstraints.py
manipulatorConstraints/jointPositionLimits.py
manipulatorConstraints/jointVelocityConstraints.py
manipulatorConstraints/robustJointPositionLimits.py
manipulatorConstraints/robustJointVelocityConstraints.py
manipulatorConstraints/torqueLimitConstraints.py
manipulatorTasks/__init__.py
manipulatorTasks/admittanceTask.py
manipulatorTasks/contactAdmittanceTask.py
manipulatorTasks/maxContactVelTask.py
manipulatorTasks/maxImpactForceTask.py
manipulatorTasks/orientationTask.py
manipulatorTasks/positionTask.py
manipulatorTasks/trajectoryTask.py
manipulatorTasks/translationVelocityTask.py
pyQpController-0.0.1.dist-info/DESCRIPTION.rst
pyQpController-0.0.1.dist-info/METADATA
pyQpController-0.0.1.dist-info/RECORD
pyQpController-0.0.1.dist-info/WHEEL
pyQpController-0.0.1.dist-info/metadata.json
pyQpController-0.0.1.dist-info/top_level.txt
qpControllers/__init__.py
qpControllers/manipulatorQP.py
qpControllers/qpObj.py
worlds/__init__.py
worlds/cubes_KR_R650.py
