Metadata-Version: 2.0
Name: pyQpController
Version: 0.0.1
Summary: Python implementation of a multi-objective controller using quadratic programming.
Home-page: https://github.com/wyqsnddd/pyQpController
Author: Yuquan Wang
Author-email: wyqsnddd@gmail.com
License: UNKNOWN
Platform: UNKNOWN
Classifier: Programming Language :: Python :: 3
Classifier: License :: OSI Approved :: GNU Lesser General Public License v3 (LGPLv3)
Classifier: Operating System :: OS Independent
Requires-Python: >=3.6
Requires-Dist: pydart2
